[
    {
      "firstName": "Carrie",
      "lastName": "Dale",
      "login": "Carrie26",
      "mail": "Carrie26@o2.pl",
      "dateOfBirth": "2017-02-18T06:49:06",
      "description": "Consequat consectetur occaecat officia elit id pariatur ad.",
      "mainPhotoUrl": "https://res.cloudinary.com/mazicloud/image/upload/v1612782933/siatkowka_xocvz2.png"
    },
    {
      "firstName": "Villarreal",
      "lastName": "Oneal",
      "login": "Villarreal46",
      "mail": "Villarreal46@o2.pl",
      "dateOfBirth": "1995-02-09T12:17:54",
      "description": "Ea anim sit commodo qui veniam reprehenderit quis consectetur.",
      "mainPhotoUrl": "https://res.cloudinary.com/mazicloud/image/upload/v1612782930/hokej_w0kd9f.png"
    },
    {
      "firstName": "Cassie",
      "lastName": "Robbins",
      "login": "Cassie98",
      "mail": "Cassie98@o2.pl",
      "dateOfBirth": "1993-02-02T01:26:41",
      "description": "Ut nostrud ipsum et proident consequat aliqua duis dolore cupidatat ex.",
      "mainPhotoUrl": "https://res.cloudinary.com/mazicloud/image/upload/v1612782933/siatkowka_xocvz2.png"
    },
    {
      "firstName": "Prince",
      "lastName": "Cleveland",
      "login": "Prince47",
      "mail": "Prince47@o2.pl",
      "dateOfBirth": "1988-02-28T07:13:22",
      "description": "Labore nisi dolore non esse ullamco deserunt ut.",
      "mainPhotoUrl": "https://res.cloudinary.com/mazicloud/image/upload/v1612782934/pilka_nozna_auhio3.png"
    },
    {
      "firstName": "Stephens",
      "lastName": "Glover",
      "login": "Stephens50",
      "mail": "Stephens50@o2.pl",
      "dateOfBirth": "2010-07-29T10:48:25",
      "description": "Fugiat ad anim id duis eiusmod.",
      "mainPhotoUrl": "https://res.cloudinary.com/mazicloud/image/upload/v1612782933/siatkowka_xocvz2.png"
    },
    {
      "firstName": "Teresa",
      "lastName": "House",
      "login": "Teresa4",
      "mail": "Teresa4@o2.pl",
      "dateOfBirth": "1996-02-11T10:50:22",
      "description": "Duis Lorem tempor nulla pariatur non labore Lorem irure laboris cillum.",
      "mainPhotoUrl": "https://res.cloudinary.com/mazicloud/image/upload/v1612782934/pilka_nozna_auhio3.png"
    },
    {
      "firstName": "Wilcox",
      "lastName": "Hinton",
      "login": "Wilcox93",
      "mail": "Wilcox93@o2.pl",
      "dateOfBirth": "1998-06-08T06:41:53",
      "description": "Magna non tempor id in.",
      "mainPhotoUrl": "https://res.cloudinary.com/mazicloud/image/upload/v1612782932/basketball_cmvnte.png"
    },
    {
      "firstName": "Sullivan",
      "lastName": "Whitehead",
      "login": "Sullivan80",
      "mail": "Sullivan80@o2.pl",
      "dateOfBirth": "1985-04-23T01:01:51",
      "description": "Adipisicing eiusmod do dolor ipsum nulla non adipisicing.",
      "mainPhotoUrl": "https://res.cloudinary.com/mazicloud/image/upload/v1612782930/pad_jmzggj.png"
    },
    {
      "firstName": "Pennington",
      "lastName": "Hall",
      "login": "Pennington46",
      "mail": "Pennington46@o2.pl",
      "dateOfBirth": "2010-11-15T11:42:22",
      "description": "Aliqua excepteur est occaecat excepteur est qui nulla eu duis consectetur.",
      "mainPhotoUrl": "https://res.cloudinary.com/mazicloud/image/upload/v1612782932/basketball_cmvnte.png"
    },
    {
      "firstName": "Norma",
      "lastName": "Hopkins",
      "login": "Norma69",
      "mail": "Norma69@o2.pl",
      "dateOfBirth": "2021-03-07T12:09:23",
      "description": "Laborum aliquip tempor reprehenderit enim aliqua duis.",
      "mainPhotoUrl": "https://res.cloudinary.com/mazicloud/image/upload/v1612782934/pilka_nozna_auhio3.png"
    },
    {
      "firstName": "Banks",
      "lastName": "Bartlett",
      "login": "Banks39",
      "mail": "Banks39@o2.pl",
      "dateOfBirth": "1980-06-14T06:10:19",
      "description": "Pariatur adipisicing ullamco exercitation culpa aute elit anim tempor ullamco ea excepteur ea minim.",
      "mainPhotoUrl": "https://res.cloudinary.com/mazicloud/image/upload/v1612782932/basketball_cmvnte.png"
    },
    {
      "firstName": "Benton",
      "lastName": "Drake",
      "login": "Benton38",
      "mail": "Benton38@o2.pl",
      "dateOfBirth": "2013-04-25T07:54:49",
      "description": "Lorem ad voluptate tempor ad in minim minim consequat.",
      "mainPhotoUrl": "https://res.cloudinary.com/mazicloud/image/upload/v1612782933/siatkowka_xocvz2.png"
    },
    {
      "firstName": "Abigail",
      "lastName": "Jensen",
      "login": "Abigail37",
      "mail": "Abigail37@o2.pl",
      "dateOfBirth": "2003-02-20T04:29:58",
      "description": "Non nisi elit sunt amet ipsum tempor irure.",
      "mainPhotoUrl": "https://res.cloudinary.com/mazicloud/image/upload/v1612782930/pad_jmzggj.png"
    },
    {
      "firstName": "Witt",
      "lastName": "Wagner",
      "login": "Witt43",
      "mail": "Witt43@o2.pl",
      "dateOfBirth": "1971-09-14T12:01:35",
      "description": "Irure occaecat officia aute cupidatat exercitation mollit deserunt proident officia excepteur esse voluptate fugiat.",
      "mainPhotoUrl": "https://res.cloudinary.com/mazicloud/image/upload/v1612782932/basketball_cmvnte.png"
    },
    {
      "firstName": "Marianne",
      "lastName": "Bradshaw",
      "login": "Marianne7",
      "mail": "Marianne7@o2.pl",
      "dateOfBirth": "1998-02-18T03:14:55",
      "description": "Adipisicing voluptate qui voluptate adipisicing sint reprehenderit.",
      "mainPhotoUrl": "https://res.cloudinary.com/mazicloud/image/upload/v1612782930/hokej_w0kd9f.png"
    },
    {
      "firstName": "Alexandra",
      "lastName": "Nolan",
      "login": "Alexandra62",
      "mail": "Alexandra62@o2.pl",
      "dateOfBirth": "1981-01-27T11:14:24",
      "description": "Veniam ipsum est veniam proident.",
      "mainPhotoUrl": "https://res.cloudinary.com/mazicloud/image/upload/v1612782934/pilka_nozna_auhio3.png"
    },
    {
      "firstName": "Elsie",
      "lastName": "Mccoy",
      "login": "Elsie47",
      "mail": "Elsie47@o2.pl",
      "dateOfBirth": "1985-06-11T12:25:45",
      "description": "Culpa fugiat pariatur minim est eiusmod est laborum exercitation est ut mollit sunt.",
      "mainPhotoUrl": "https://res.cloudinary.com/mazicloud/image/upload/v1612782930/hokej_w0kd9f.png"
    },
    {
      "firstName": "Figueroa",
      "lastName": "Nielsen",
      "login": "Figueroa97",
      "mail": "Figueroa97@o2.pl",
      "dateOfBirth": "1970-01-10T03:15:22",
      "description": "Non velit in ad aute do incididunt enim sint enim do.",
      "mainPhotoUrl": "https://res.cloudinary.com/mazicloud/image/upload/v1612782929/bieg_icib7u.png"
    },
    {
      "firstName": "Watts",
      "lastName": "Weber",
      "login": "Watts6",
      "mail": "Watts6@o2.pl",
      "dateOfBirth": "1998-12-26T03:01:27",
      "description": "Lorem deserunt reprehenderit non laboris ea ea do.",
      "mainPhotoUrl": "https://res.cloudinary.com/mazicloud/image/upload/v1612782932/pletka_pkk7ze.png"
    },
    {
      "firstName": "Kaye",
      "lastName": "Pitts",
      "login": "Kaye28",
      "mail": "Kaye28@o2.pl",
      "dateOfBirth": "1981-11-06T07:05:39",
      "description": "Pariatur fugiat enim pariatur elit voluptate elit voluptate commodo non.",
      "mainPhotoUrl": "https://res.cloudinary.com/mazicloud/image/upload/v1612782933/siatkowka_xocvz2.png"
    },
    {
      "firstName": "Jeannine",
      "lastName": "Clark",
      "login": "Jeannine22",
      "mail": "Jeannine22@o2.pl",
      "dateOfBirth": "2019-12-12T07:52:25",
      "description": "Do non tempor in in duis et qui elit fugiat tempor amet duis ad.",
      "mainPhotoUrl": "https://res.cloudinary.com/mazicloud/image/upload/v1612782932/basketball_cmvnte.png"
    },
    {
      "firstName": "Bond",
      "lastName": "Farley",
      "login": "Bond4",
      "mail": "Bond4@o2.pl",
      "dateOfBirth": "1991-01-20T01:19:06",
      "description": "Lorem non proident ea culpa nisi irure sunt commodo.",
      "mainPhotoUrl": "https://res.cloudinary.com/mazicloud/image/upload/v1612782934/pilka_nozna_auhio3.png"
    },
    {
      "firstName": "Cassandra",
      "lastName": "Lynn",
      "login": "Cassandra83",
      "mail": "Cassandra83@o2.pl",
      "dateOfBirth": "1984-10-06T08:13:17",
      "description": "Ea amet pariatur elit consectetur aliquip ipsum officia nisi deserunt quis ea.",
      "mainPhotoUrl": "https://res.cloudinary.com/mazicloud/image/upload/v1612782929/bieg_icib7u.png"
    },
    {
      "firstName": "Jean",
      "lastName": "Beach",
      "login": "Jean56",
      "mail": "Jean56@o2.pl",
      "dateOfBirth": "1982-10-16T09:29:06",
      "description": "Ea ad sint nostrud cillum voluptate minim duis irure velit Lorem non.",
      "mainPhotoUrl": "https://res.cloudinary.com/mazicloud/image/upload/v1612782933/siatkowka_xocvz2.png"
    },
    {
      "firstName": "Robbie",
      "lastName": "Rasmussen",
      "login": "Robbie7",
      "mail": "Robbie7@o2.pl",
      "dateOfBirth": "1981-09-07T09:05:30",
      "description": "Amet excepteur proident consectetur nulla velit culpa incididunt labore voluptate nisi exercitation cillum ut ut.",
      "mainPhotoUrl": "https://res.cloudinary.com/mazicloud/image/upload/v1612782933/siatkowka_xocvz2.png"
    },
    {
      "firstName": "Cecelia",
      "lastName": "Baxter",
      "login": "Cecelia89",
      "mail": "Cecelia89@o2.pl",
      "dateOfBirth": "1984-02-01T10:55:36",
      "description": "Duis eiusmod ut ullamco velit labore consequat et sit velit proident.",
      "mainPhotoUrl": "https://res.cloudinary.com/mazicloud/image/upload/v1612782933/siatkowka_xocvz2.png"
    },
    {
      "firstName": "Melendez",
      "lastName": "Browning",
      "login": "Melendez21",
      "mail": "Melendez21@o2.pl",
      "dateOfBirth": "2015-03-15T10:17:54",
      "description": "Incididunt dolor reprehenderit amet exercitation adipisicing dolore.",
      "mainPhotoUrl": "https://res.cloudinary.com/mazicloud/image/upload/v1612782932/basketball_cmvnte.png"
    },
    {
      "firstName": "Angelica",
      "lastName": "Benjamin",
      "login": "Angelica74",
      "mail": "Angelica74@o2.pl",
      "dateOfBirth": "1973-03-23T09:47:20",
      "description": "Do deserunt exercitation in duis esse mollit sunt ea non enim.",
      "mainPhotoUrl": "https://res.cloudinary.com/mazicloud/image/upload/v1612782932/basketball_cmvnte.png"
    },
    {
      "firstName": "Flores",
      "lastName": "Skinner",
      "login": "Flores41",
      "mail": "Flores41@o2.pl",
      "dateOfBirth": "1990-01-13T11:11:51",
      "description": "Minim mollit eiusmod irure incididunt mollit enim voluptate nulla commodo reprehenderit exercitation do fugiat officia.",
      "mainPhotoUrl": "https://res.cloudinary.com/mazicloud/image/upload/v1612782934/pilka_nozna_auhio3.png"
    },
    {
      "firstName": "Russell",
      "lastName": "Hicks",
      "login": "Russell15",
      "mail": "Russell15@o2.pl",
      "dateOfBirth": "1998-12-14T09:53:51",
      "description": "Nostrud consequat veniam qui fugiat anim irure exercitation mollit deserunt reprehenderit occaecat irure.",
      "mainPhotoUrl": "https://res.cloudinary.com/mazicloud/image/upload/v1612782932/basketball_cmvnte.png"
    }
  ]



 